demoshell/__main__.py
demoshell/main.py
demoshell-0.2.0.dist-info/DESCRIPTION.rst
demoshell-0.2.0.dist-info/METADATA
demoshell-0.2.0.dist-info/RECORD
demoshell-0.2.0.dist-info/WHEEL
demoshell-0.2.0.dist-info/entry_points.txt
demoshell-0.2.0.dist-info/metadata.json
demoshell-0.2.0.dist-info/pbr.json
demoshell-0.2.0.dist-info/top_level.txt
