Metadata-Version: 2.0
Name: demoshell
Version: 0.2.0
Summary: Simplified Shell for Live Demos
Home-page: https://pypi.python.org/pypi/demoshell
Author: Doug Hellmann
Author-email: doug@doughellmann.com
License: UNKNOWN
Platform: UNKNOWN
Classifier: Development Status :: 3 - Alpha
Classifier: Environment :: Console
Classifier: Intended Audience :: Developers
Classifier: Intended Audience :: Education
Classifier: Intended Audience :: End Users/Desktop
Classifier: Intended Audience :: Information Technology
Classifier: Intended Audience :: Science/Research
Classifier: License :: OSI Approved :: Apache Software License
Classifier: Programming Language :: Python
Classifier: Programming Language :: Python :: 3
Requires-Dist: urwid (>=2.0.1)
Requires-Dist: appdirs (>=1.4.3)
Provides-Extra: test
Requires-Dist: flake8; extra == 'test'
